stac_fastapi/sfeos_helpers/mappings.py
stac_fastapi/sfeos_helpers/version.py
stac_fastapi/sfeos_helpers/aggregation/README.md
stac_fastapi/sfeos_helpers/aggregation/__init__.py
stac_fastapi/sfeos_helpers/aggregation/client.py
stac_fastapi/sfeos_helpers/aggregation/format.py
stac_fastapi/sfeos_helpers/database/README.md
stac_fastapi/sfeos_helpers/database/__init__.py
stac_fastapi/sfeos_helpers/database/catalogs.py
stac_fastapi/sfeos_helpers/database/datetime.py
stac_fastapi/sfeos_helpers/database/document.py
stac_fastapi/sfeos_helpers/database/index.py
stac_fastapi/sfeos_helpers/database/mapping.py
stac_fastapi/sfeos_helpers/database/query.py
stac_fastapi/sfeos_helpers/database/utils.py
stac_fastapi/sfeos_helpers/filter/README.md
stac_fastapi/sfeos_helpers/filter/__init__.py
stac_fastapi/sfeos_helpers/filter/client.py
stac_fastapi/sfeos_helpers/filter/cql2.py
stac_fastapi/sfeos_helpers/filter/transform.py
stac_fastapi/sfeos_helpers/models/patch.py
stac_fastapi/sfeos_helpers/search_engine/__init__.py
stac_fastapi/sfeos_helpers/search_engine/base.py
stac_fastapi/sfeos_helpers/search_engine/factory.py
stac_fastapi/sfeos_helpers/search_engine/index_operations.py
stac_fastapi/sfeos_helpers/search_engine/inserters.py
stac_fastapi/sfeos_helpers/search_engine/managers.py
stac_fastapi/sfeos_helpers/search_engine/selection/__init__.py
stac_fastapi/sfeos_helpers/search_engine/selection/base.py
stac_fastapi/sfeos_helpers/search_engine/selection/cache_manager.py
stac_fastapi/sfeos_helpers/search_engine/selection/factory.py
stac_fastapi/sfeos_helpers/search_engine/selection/selectors.py
sfeos_helpers-6.10.0.dist-info/METADATA
sfeos_helpers-6.10.0.dist-info/WHEEL
sfeos_helpers-6.10.0.dist-info/RECORD
