Metadata-Version: 2.4
Name: sfeos_helpers
Version: 6.10.0
Summary: Helper library for the Elasticsearch and Opensearch stac-fastapi backends.
Project-URL: Homepage, https://github.com/stac-utils/stac-fastapi-elasticsearch-opensearch
License: MIT
Keywords: Elasticsearch,FastAPI,Opensearch,STAC,STAC-API,stac-fastapi
Classifier: Intended Audience :: Developers
Classifier: Intended Audience :: Information Technology
Classifier: Intended Audience :: Science/Research
Classifier: License :: OSI Approved :: MIT License
Classifier: Programming Language :: Python :: 3.11
Classifier: Programming Language :: Python :: 3.12
Classifier: Programming Language :: Python :: 3.13
Classifier: Programming Language :: Python :: 3.14
Requires-Python: >=3.11
Requires-Dist: stac-fastapi-core==6.10.0
